Workbook

Sheet Read Me
B2: JPMorgan Chase & Co. (NYSE: JPM)
B3: Bank Analysis & Valuation — lite version (FY2022-25 history + one valuation method)
B5: WHAT THIS IS
B6: A focused, defensible bank case: four years of JPM's actual results, the key bank ratios computed from
B7: the source data, and one valuation method (justified P/B vs ROE). Built to be understood end-to-end.
B9: HOW IT IS BUILT (read this — it answers 'did you just hardcode it?')
B10: Only genuine reported facts are typed in (blue): revenue, expense, provision, net income, share counts,
B11: book value. Everything that can be derived is a live formula (black): noninterest revenue, pre-provision
B12: profit, pre-tax, the tax plug, EPS, common & tangible equity, ROE, ROTCE, efficiency, credit cost — and
B13: the entire valuation. Change any blue cell and the model recomputes.
B15: THE ONE IDEA TO OWN
B16: A bank cannot be valued like a normal company. Deposits are raw material, not financing, so there is no
... B30: Price ~$334 (Jun 2026). All figures illustrative — re-derive before quoting in an interview.

Sheet Model
A1: JPMorgan Chase & Co. — Historicals & Ratios
A2: $ in millions unless stated | FY ends 31 Dec | blue = reported input, black = formula
B4: FY2022 | C4: FY2023 | D4: FY2024 | E4: FY2025 | G4: Notes
A5: INCOME STATEMENT ($mm)
A6: Net interest income (managed) | B6: 66710 | C6: 89700 | D6: 93100 | E6: 95500 | G6: Managed basis (FY results).
A7: Noninterest revenue | B7: =B8-B6 -> 61985 | C7: =C8-C6 -> 68404 | D7: =D8-D6 -> 84456 | E7: =E8-E6 -> 86947 | G7: Total revenue less NII.
A8: Total net revenue | B8: 128695 | C8: 158104 | D8: 177556 | E8: 182447 | G8: Reported total net revenue (Annual Reports).
A9: Noninterest expense | B9: 76140 | C9: 87172 | D9: 91797 | E9: 95640
A10: Pre-provision profit | B10: =B8-B9 -> 52555 | C10: =C8-C9 -> 70932 | D10: =D8-D9 -> 85759 | E10: =E8-E9 -> 86807
A11: Provision for credit losses | B11: 6389 | C11: 9320 | D11: 10678 | E11: 14212
A12: Pre-tax income | B12: =B10-B11 -> 46166 | C12: =C10-C11 -> 61612 | D12: =D10-D11 -> 75081 | E12: =E10-E11 -> 72595
A13: Income tax (derived) | B13: =B12-B14 -> 8490 | C13: =C12-C14 -> 12060 | D13: =D12-D14 -> 16610 | E13: =E12-E14 -> 15547 | G13: Pre-tax less reported net income (the plug).
A14: Net income | B14: 37676 | C14: 49552 | D14: 58471 | E14: 57048 | G14: Reported net income.
A15: Preferred dividends | B15: 1784 | C15: 1752 | D15: 1571 | E15: 1348
A16: Net income to common | B16: =B14-B15 -> 35892 | C16: =C14-C15 -> 47800 | D16: =D14-D15 -> 56900 | E16: =E14-E15 -> 55700
A18: PER SHARE & RETURNS
A19: Avg diluted shares (mm) | B19: 2969 | C19: 2945 | D19: 2881 | E19: 2782 | G19: Reported diluted share count.
A20: Diluted EPS ($) | B20: =B16/B19 -> 12.088919 | C20: =C16/C19 -> 16.2309 | D20: =D16/D19 -> 19.750087 | E20: =E16/E19 -> 20.021567 | G20: NI to common div by shares; ties to reported EPS.
A21: Dividend per share ($) | B21: 4 | C21: 4.1 | D21: 4.8 | E21: 5.8
A22: Book value per share ($) | B22: 90.29 | C22: 104.45 | D22: 116.07 | E22: 126.99
A23: Tangible BVPS ($) | B23: 73.12 | C23: 86.08 | D23: 97.3 | E23: 107.56
A24: Period-end shares (mm) | B24: 2929 | C24: 2898 | D24: 2788 | E24: 2695 | G24: Period-end common shares.
A25: Common equity ($mm) | B25: =B22*B24 -> 264459.41 | C25: =C22*C24 -> 302696.1 | D25: =D22*D24 -> 323603.16 | E25: =E22*E24 -> 342238.05 | G25: BVPS x period-end shares.
A26: Avg common equity ($mm) | C26: =(B25+C25)/2 -> 283577.76 | D26: =(C25+D25)/2 -> 313149.63 | E26: =(D25+E25)/2 -> 332920.6
A27: Tangible common equity ($mm) | B27: =B23*B24 -> 214168.48 | C27: =C23*C24 -> 249459.84 | D27: =D23*D24 -> 271272.4 | E27: =E23*E24 -> 289874.2
A28: Avg tangible common equity ($mm) | C28: =(B27+C27)/2 -> 231814.16 | D28: =(C27+D27)/2 -> 260366.12 | E28: =(D27+E27)/2 -> 280573.3
A29: ROE (%) | B29: 0.14 | C29: =C16/C26 -> 0.16856047 | D29: =D16/D26 -> 0.18170227 | E29: =E16/E26 -> 0.16730716 | G29: 2022 reported (base year); 2023-25 computed on avg equity.
A30: ROTCE (%) | B30: 0.18 | C30: =C16/C28 -> 0.20619966 | D30: =D16/D28 -> 0.21853842 | E30: =E16/E28 -> 0.1985221
A32: KEY RATIOS & SCALE
A33: Avg loans ($B) | B33: 1080 | C33: 1250 | D33: 1325 | E33: 1450 | G33: Approx average; reconcile to 10-K.
A34: Avg deposits ($B) | B34: 2400 | C34: 2375 | D34: 2400 | E34: 2570
A35: Efficiency ratio (%) | B35: =B9/B8 -> 0.59163138 | C35: =C9/C8 -> 0.5513586 | D35: =D9/D8 -> 0.51700309 | E35: =E9/E8 -> 0.52420703 | G35: Expense div by total revenue.
A36: Credit cost (% avg loans) | B36: =B11/(B33*1000) -> 0.0059157407 | C36: =C11/(C33*1000) -> 0.007456 | D36: =D11/(D33*1000) -> 0.0080588679 | E36: =E11/(E33*1000) -> 0.0098013793 | G36: Provision div by avg loans.
A37: Net interest margin (%) | B37: 0.0197 | C37: 0.0262 | D37: 0.0263 | E37: 0.025 | G37: Reported (2022 approx).
A38: CET1 ratio (%) | B38: 0.132 | C38: 0.15 | D38: 0.157 | E38: 0.146

Sheet Valuation
A1: JPMorgan Chase & Co. — Valuation
A2: One method: justified P/B vs ROE, applied to FY2025 book value. Green = linked from Model.
A4: MARKET (Jun 2026)
A5: Share price ($) | B5: 334
A6: Shares outstanding (mm) | B6: =Model!E24 -> 2695
A7: Market cap ($mm) | B7: =B5*B6 -> 900130
A9: CURRENT MULTIPLES (FY2025 actuals)
A10: P/E (trailing) | B10: =B5/Model!E20 -> 16.682011
A11: P/B | B11: =B5/Model!E22 -> 2.6301284
A12: P/TBV | B12: =B5/Model!E23 -> 3.1052436
A13: Dividend yield | B13: =Model!E21/B5 -> 0.017365269
A15: COST OF EQUITY (CAPM)
A16: Risk-free rate (10Y UST) | B16: 0.043
A17: Beta | B17: 1
A18: Equity risk premium | B18: 0.048
A19: Cost of equity (COE) | B19: =B16+B17*B18 -> 0.091
A21: VALUATION ASSUMPTIONS
A22: Normalised ROE | B22: 0.17
A23: Long-term growth (g) | B23: 0.04
A24: FY2025 book value/share ($) | B24: =Model!E22 -> 126.99
A26: JUSTIFIED P/B VALUATION
A27: Justified P/B = (ROE - g)/(COE - g) | B27: =(B22-B23)/(B19-B23) -> 2.5490196
A28: Target price = Justified P/B x BVPS | B28: =B27*B24 -> 323.7
A29: Upside / (downside) vs price | B29: =B28/B5-1 -> -0.030838323
A30: Rating | B30: =IF(B29>0.1,"OVERWEIGHT / BUY",IF(B29>-0.1,"NEUTRAL / HOLD","UNDERWEIGHT / SELL")) -> NEUTRAL / HOLD
A32: REALITY CHECK — what ROE does today's price imply?
A33: Market-implied ROE at current price | B33: =B11*(B19-B23)+B23 -> 0.17413655
A35: SENSITIVITY — target price ($): rows = COE, cols = normalised ROE
D36: COE \ ROE | E36: 0.15 | F36: 0.16 | G36: 0.17
D37: 0.085 | E37: =((E$36-$B$23)/($D37-$B$23))*$B$24 -> 310.42 | F37: =((F$36-$B$23)/($D37-$B$23))*$B$24 -> 338.64 | G37: =((G$36-$B$23)/($D37-$B$23))*$B$24 -> 366.86
D38: 0.09 | E38: =((E$36-$B$23)/($D38-$B$23))*$B$24 -> 279.378 | F38: =((F$36-$B$23)/($D38-$B$23))*$B$24 -> 304.776 | G38: =((G$36-$B$23)/($D38-$B$23))*$B$24 -> 330.174
D39: 0.095 | E39: =((E$36-$B$23)/($D39-$B$23))*$B$24 -> 253.98 | F39: =((F$36-$B$23)/($D39-$B$23))*$B$24 -> 277.06909 | G39: =((G$36-$B$23)/($D39-$B$23))*$B$24 -> 300.15818
D40: 0.1 | E40: =((E$36-$B$23)/($D40-$B$23))*$B$24 -> 232.815 | F40: =((F$36-$B$23)/($D40-$B$23))*$B$24 -> 253.98 | G40: =((G$36-$B$23)/($D40-$B$23))*$B$24 -> 275.145
D41: 0.105 | E41: =((E$36-$B$23)/($D41-$B$23))*$B$24 -> 214.90615 | F41: =((F$36-$B$23)/($D41-$B$23))*$B$24 -> 234.44308 | G41: =((G$36-$B$23)/($D41-$B$23))*$B$24 -> 253.98
